README.md
setup.py
reportTelegram/__init__.py
reportTelegram/__main__.py
reportTelegram/admin.py
reportTelegram/reportBot.py
reportTelegram/reports.py
reportTelegram/utils.py
reportTelegram/variables.py
reportTelegram.egg-info/PKG-INFO
reportTelegram.egg-info/SOURCES.txt
reportTelegram.egg-info/dependency_links.txt
reportTelegram.egg-info/not-zip-safe
reportTelegram.egg-info/requires.txt
reportTelegram.egg-info/top_level.txt
reportTelegram/data/stickers/banned.webp
reportTelegram/data/stickers/nancy.webp