Metadata-Version: 1.0
Name: reportTelegram
Version: 0.4.3
Summary: A telegram bot that helps you to keep the group clean by a report system with kicks and ban times.
Home-page: https://github.com/jossalgon/reportTelegram
Author: Jose Luis Salazar Gonzalez
Author-email: joseluis25sg@gmail.com
License: UNKNOWN
Platform: UNKNOWN
